indianapy/__init__.py
indianapy-0.1.1.dist-info/WHEEL
indianapy-0.1.1.dist-info/METADATA
indianapy-0.1.1.dist-info/RECORD
